<?xml version="1.0" encoding="UTF-8"?>
<!DOCTYPE mapper PUBLIC "-//mybatis.org//DTD Mapper 3.0//EN" "http://mybatis.org/dtd/mybatis-3-mapper.dtd">
<mapper namespace="com.work.dao.CostMapper">
  <resultMap id="BaseResultMap" type="com.work.pojo.Cost">
    <!--
      WARNING - @mbg.generated
      This element is automatically generated by MyBatis Generator, do not modify.
    -->
    <id column="id" jdbcType="INTEGER" property="id" />
    <result column="shop" jdbcType="DOUBLE" property="shop" />
    <result column="sp_message" jdbcType="VARCHAR" property="spMessage" />
    <result column="meat" jdbcType="DOUBLE" property="meat" />
    <result column="mt_message" jdbcType="VARCHAR" property="mtMessage" />
    <result column="house" jdbcType="DOUBLE" property="house" />
    <result column="he_message" jdbcType="VARCHAR" property="heMessage" />
    <result column="travel" jdbcType="DOUBLE" property="travel" />
    <result column="tl_message" jdbcType="VARCHAR" property="tlMessage" />
    <result column="lark" jdbcType="DOUBLE" property="lark" />
    <result column="lk_message" jdbcType="VARCHAR" property="lkMessage" />
    <result column="lend" jdbcType="DOUBLE" property="lend" />
    <result column="ld_message" jdbcType="VARCHAR" property="ldMessage" />
    <result column="ct_repay" jdbcType="DOUBLE" property="ctRepay" />
    <result column="cry_message" jdbcType="VARCHAR" property="cryMessage" />
    <result column="ct_date" jdbcType="DATE" property="ctDate" />
    <result column="uid" jdbcType="INTEGER" property="uid" />
  </resultMap>
  <delete id="deleteByPrimaryKey" parameterType="java.lang.Integer">
    <!--
      WARNING - @mbg.generated
      This element is automatically generated by MyBatis Generator, do not modify.
    -->
    delete from cost
    where id = #{id,jdbcType=INTEGER}
  </delete>
  <insert id="insert" parameterType="com.work.pojo.Cost">
    <!--
      WARNING - @mbg.generated
      This element is automatically generated by MyBatis Generator, do not modify.
    -->
    insert into cost (id, shop, sp_message, 
      meat, mt_message, house, 
      he_message, travel, tl_message, 
      lark, lk_message, lend, 
      ld_message, ct_repay, cry_message, 
      ct_date, uid)
    values (#{id,jdbcType=INTEGER}, #{shop,jdbcType=DOUBLE}, #{spMessage,jdbcType=VARCHAR}, 
      #{meat,jdbcType=DOUBLE}, #{mtMessage,jdbcType=VARCHAR}, #{house,jdbcType=DOUBLE}, 
      #{heMessage,jdbcType=VARCHAR}, #{travel,jdbcType=DOUBLE}, #{tlMessage,jdbcType=VARCHAR}, 
      #{lark,jdbcType=DOUBLE}, #{lkMessage,jdbcType=VARCHAR}, #{lend,jdbcType=DOUBLE}, 
      #{ldMessage,jdbcType=VARCHAR}, #{ctRepay,jdbcType=DOUBLE}, #{cryMessage,jdbcType=VARCHAR}, 
      #{ctDate,jdbcType=DATE}, #{uid,jdbcType=INTEGER})
  </insert>
  <update id="updateByPrimaryKey" parameterType="com.work.pojo.Cost">
    <!--
      WARNING - @mbg.generated
      This element is automatically generated by MyBatis Generator, do not modify.
    -->
    update cost
    set shop = #{shop,jdbcType=DOUBLE},
      sp_message = #{spMessage,jdbcType=VARCHAR},
      meat = #{meat,jdbcType=DOUBLE},
      mt_message = #{mtMessage,jdbcType=VARCHAR},
      house = #{house,jdbcType=DOUBLE},
      he_message = #{heMessage,jdbcType=VARCHAR},
      travel = #{travel,jdbcType=DOUBLE},
      tl_message = #{tlMessage,jdbcType=VARCHAR},
      lark = #{lark,jdbcType=DOUBLE},
      lk_message = #{lkMessage,jdbcType=VARCHAR},
      lend = #{lend,jdbcType=DOUBLE},
      ld_message = #{ldMessage,jdbcType=VARCHAR},
      ct_repay = #{ctRepay,jdbcType=DOUBLE},
      cry_message = #{cryMessage,jdbcType=VARCHAR},
      ct_date = #{ctDate,jdbcType=DATE},
      uid = #{uid,jdbcType=INTEGER}
    where id = #{id,jdbcType=INTEGER}
  </update>
  <select id="selectByPrimaryKey" parameterType="java.lang.Integer" resultMap="BaseResultMap">
    <!--
      WARNING - @mbg.generated
      This element is automatically generated by MyBatis Generator, do not modify.
    -->
    select id, shop, sp_message, meat, mt_message, house, he_message, travel, tl_message, 
    lark, lk_message, lend, ld_message, ct_repay, cry_message, ct_date, uid
    from cost
    where id = #{id,jdbcType=INTEGER}
  </select>
  <select id="selectAll" resultMap="BaseResultMap">
    <!--
      WARNING - @mbg.generated
      This element is automatically generated by MyBatis Generator, do not modify.
    -->
    select id, shop, sp_message, meat, mt_message, house, he_message, travel, tl_message, 
    lark, lk_message, lend, ld_message, ct_repay, cry_message, ct_date, uid
    from cost
  </select>
</mapper>